{"id":"r5i1tpbbbq4mbhi35y5j5xw","title":"Recursion","desc":"","updated":1647705341090,"created":1647602437869,"custom":{},"fname":"lang.haskell.recursion","type":"note","vault":{"fsPath":"vault"},"contentHash":"1c809b8ee9315ef4f3a95af25ed07369","links":[],"anchors":{"why-is-it-useful":{"type":"header","text":"Why is it useful?","value":"why-is-it-useful","line":8,"column":0,"depth":2},"how-to-think-recursively":{"type":"header","text":"How to think recursively","value":"how-to-think-recursively","line":19,"column":0,"depth":2}},"children":[],"parent":"ojnogx9md793ue6tbc59sdd","data":{}}
